Task 02 and 03/Decoder.v
module Decoder (
    input wire [3:0] BCD, // 4-bit BCD input
    output reg [6:0] seg  // 7-segment output (a to g)
);

    // Always block to decode BCD to 7-segment
    always @(BCD) begin
        case (BCD)
            4'b0000: seg = 7'b0111111;  // 0
            4'b0001: seg = 7'b0000110;  // 1
            4'b0010: seg = 7'b1011011;  // 2
            4'b0011: seg = 7'b1001111;  // 3
            4'b0100: seg = 7'b1100110;  // 4
            4'b0101: seg = 7'b1101101;  // 5
            4'b0110: seg = 7'b1111101;  // 6
            4'b0111: seg = 7'b0000111;  // 7
            4'b1000: seg = 7'b1111111;  // 8
            4'b1001: seg = 7'b1101111;  // 9
            default: seg = 7'b0000000;  // Blank or error state
        endcase
    end

endmodule

Task 02 and 03/Counter.v
module Counter (
    input wire clk,        // Clock input
    input wire reset,      // Reset input
    output wire [6:0] seg_tens,  // 7-segment display for tens
    output wire [6:0] seg_ones   // 7-segment display for ones
);

    reg [5:0] count; // 6-bit counter to count up to 40
    wire [3:0] tens, ones; // BCD digits for tens and ones

    // Increment the counter on each clock pulse
    always @(posedge clk or posedge reset) begin
        if (reset) begin
            count <= 6'b0; // Reset the counter to 0
        end else if (count == 6'd40) begin
            count <= 6'b0; // Reset the counter when it reaches P (40)
        end else begin
            count <= count + 1; // Increment the counter
        end
    end

    // Convert the count into BCD digits for tens and ones
    assign tens = count / 10; // Tens digit
    assign ones = count % 10; // Ones digit

    // Use the Decoder module to drive the 7-segment displays
    Decoder decode_tens(.BCD(tens), .seg(seg_tens));
    Decoder decode_ones(.BCD(ones), .seg(seg_ones));

endmodule

Task 02 and 03/CounterTB.v
module CounterTB();

    reg clk;       // Testbench clock
    reg reset;     // Testbench reset
    wire [6:0] seg_tens; // Tens 7-segment output
    wire [6:0] seg_ones; // Ones 7-segment output

    // Instantiate the Counter module
    Counter counter_inst (
        .clk(clk),
        .reset(reset),
        .seg_tens(seg_tens),
        .seg_ones(seg_ones)
    );

    // Clock generation
    
    initial begin
        clk = 0;
        forever #5 clk = ~clk; // Toggle the clock every 5 time units
        $dumpfile("counter_wave.vcd");
        $dumpvars(0, CounterTB);
    end

    // Simulation procedure
    initial begin
        reset = 1;     // Start with reset active
        #10 reset = 0; // Deactivate reset after 10 time units

        // Let the counter run for a few clock cycles until it counts to 40
        #415;

        $finish;       // End the simulation
    end

    // Monitoring the output
    initial begin
        $monitor("Time = %0t, Tens = %b, Ones = %b", $time, seg_tens, seg_ones);
    end

endmodule

Take Home 02/Task 02 and 03/counter_wave.vcd
$date
	Tue Oct 22 06:41:30 2024
$end
$version
	Icarus Verilog
$end
$timescale
	1s
$end
$scope module CounterTB $end
$var wire 7 ! seg_tens [6:0] $end
$var wire 7 " seg_ones [6:0] $end
$var reg 1 # clk $end
$var reg 1 $ reset $end
$scope module counter_inst $end
$var wire 1 # clk $end
$var wire 1 $ reset $end
$var wire 4 % tens [3:0] $end
$var wire 7 & seg_tens [6:0] $end
$var wire 7 ' seg_ones [6:0] $end
$var wire 4 ( ones [3:0] $end
$var reg 6 ) count [5:0] $end
$scope module decode_ones $end
$var wire 4 * BCD [3:0] $end
$var reg 7 + seg [6:0] $end
$upscope $end
$scope module decode_tens $end
$var wire 4 , BCD [3:0] $end
$var reg 7 - seg [6:0] $end
$upscope $end
$upscope $end
$upscope $end
$enddefinitions $end
$comment Show the parameter values. $end
$dumpall
$end
#0
$dumpvars
b111111 -
b0 ,
b111111 +
b0 *
b0 )
b0 (
b111111 '
b111111 &
b0 %
1$
0#
b111111 "
b111111 !
$end
#5
1#
#10
0#
0$
#15
b110 "
b110 '
b110 +
b1 (
b1 *
b1 )
1#
#20
0#
#25
b1011011 "
b1011011 '
b1011011 +
b10 (
b10 *
b10 )
1#
#30
0#
#35
b1001111 "
b1001111 '
b1001111 +
b11 (
b11 *
b11 )
1#
#40
0#
#45
b1100110 "
b1100110 '
b1100110 +
b100 (
b100 *
b100 )
1#
#50
0#
#55
b1101101 "
b1101101 '
b1101101 +
b101 (
b101 *
b101 )
1#
#60
0#
#65
b1111101 "
b1111101 '
b1111101 +
b110 (
b110 *
b110 )
1#
#70
0#
#75
b111 "
b111 '
b111 +
b111 (
b111 *
b111 )
1#
#80
0#
#85
b1111111 "
b1111111 '
b1111111 +
b1000 (
b1000 *
b1000 )
1#
#90
0#
#95
b1101111 "
b1101111 '
b1101111 +
b1001 (
b1001 *
b1001 )
1#
#100
0#
#105
b110 !
b110 &
b110 -
b111111 "
b111111 '
b111111 +
b1 %
b1 ,
b0 (
b0 *
b1010 )
1#
#110
0#
#115
b110 "
b110 '
b110 +
b1 (
b1 *
b1011 )
1#
#120
0#
#125
b1011011 "
b1011011 '
b1011011 +
b10 (
b10 *
b1100 )
1#
#130
0#
#135
b1001111 "
b1001111 '
b1001111 +
b11 (
b11 *
b1101 )
1#
#140
0#
#145
b1100110 "
b1100110 '
b1100110 +
b100 (
b100 *
b1110 )
1#
#150
0#
#155
b1101101 "
b1101101 '
b1101101 +
b101 (
b101 *
b1111 )
1#
#160
0#
#165
b1111101 "
b1111101 '
b1111101 +
b110 (
b110 *
b10000 )
1#
#170
0#
#175
b111 "
b111 '
b111 +
b111 (
b111 *
b10001 )
1#
#180
0#
#185
b1111111 "
b1111111 '
b1111111 +
b1000 (
b1000 *
b10010 )
1#
#190
0#
#195
b1101111 "
b1101111 '
b1101111 +
b1001 (
b1001 *
b10011 )
1#
#200
0#
#205
b1011011 !
b1011011 &
b1011011 -
b111111 "
b111111 '
b111111 +
b10 %
b10 ,
b0 (
b0 *
b10100 )
1#
#210
0#
#215
b110 "
b110 '
b110 +
b1 (
b1 *
b10101 )
1#
#220
0#
#225
b1011011 "
b1011011 '
b1011011 +
b10 (
b10 *
b10110 )
1#
#230
0#
#235
b1001111 "
b1001111 '
b1001111 +
b11 (
b11 *
b10111 )
1#
#240
0#
#245
b1100110 "
b1100110 '
b1100110 +
b100 (
b100 *
b11000 )
1#
#250
0#
#255
b1101101 "
b1101101 '
b1101101 +
b101 (
b101 *
b11001 )
1#
#260
0#
#265
b1111101 "
b1111101 '
b1111101 +
b110 (
b110 *
b11010 )
1#
#270
0#
#275
b111 "
b111 '
b111 +
b111 (
b111 *
b11011 )
1#
#280
0#
#285
b1111111 "
b1111111 '
b1111111 +
b1000 (
b1000 *
b11100 )
1#
#290
0#
#295
b1101111 "
b1101111 '
b1101111 +
b1001 (
b1001 *
b11101 )
1#
#300
0#
#305
b1001111 !
b1001111 &
b1001111 -
b111111 "
b111111 '
b111111 +
b11 %
b11 ,
b0 (
b0 *
b11110 )
1#
#310
0#
#315
b110 "
b110 '
b110 +
b1 (
b1 *
b11111 )
1#
#320
0#
#325
b1011011 "
b1011011 '
b1011011 +
b10 (
b10 *
b100000 )
1#
#330
0#
#335
b1001111 "
b1001111 '
b1001111 +
b11 (
b11 *
b100001 )
1#
#340
0#
#345
b1100110 "
b1100110 '
b1100110 +
b100 (
b100 *
b100010 )
1#
#350
0#
#355
b1101101 "
b1101101 '
b1101101 +
b101 (
b101 *
b100011 )
1#
#360
0#
#365
b1111101 "
b1111101 '
b1111101 +
b110 (
b110 *
b100100 )
1#
#370
0#
#375
b111 "
b111 '
b111 +
b111 (
b111 *
b100101 )
1#
#380
0#
#385
b1111111 "
b1111111 '
b1111111 +
b1000 (
b1000 *
b100110 )
1#
#390
0#
#395
b1101111 "
b1101111 '
b1101111 +
b1001 (
b1001 *
b100111 )
1#
#400
0#
#405
b1100110 !
b1100110 &
b1100110 -
b111111 "
b111111 '
b111111 +
b100 %
b100 ,
b0 (
b0 *
b101000 )
1#
#410
0#
#415
b111111 !
b111111 &
b111111 -
b0 %
b0 ,
b0 )
1#