Take Home 02/Task 01/IC7490.v
module IC7490 (
    input wire clk,    // Clock input
    input wire reset,  // Reset input
    output reg [3:0] Q // BCD output (QD, QC, QB, QA)
);

    // Always block for counting functionality
    always @(posedge clk or posedge reset) begin
        if (reset) begin
            Q <= 4'b0000; // Reset to 0
        end else begin
            if (Q == 4'b1001) begin
                Q <= 4'b0000; // Roll back to 0 after reaching 9
            end else begin
                Q <= Q + 1;   // Increment the count
            end
        end
    end

endmodule

Take Home 02/Task 01/IC7490TB.v
module IC7490TB;

    
    reg clk;
    reg reset;
    wire [3:0] Q;
    
    
    IC7490 uut (
        .clk(clk),
        .reset(reset),
        .Q(Q)
    );
    
    // Clock generation: 10ns period (100 MHz)
    initial begin
        $dumpfile("counter.vcd");
        $dumpvars(0, IC7490TB);
        clk = 0;
        forever #5 clk = ~clk; // Toggle every 5ns
    end
    
    // Test procedure
    initial begin
        // Monitor output
        $monitor("Time = %0t | Reset = %b | Count = %b", $time, reset, Q);
        
        // Initial values
        reset = 1; 
        #10 reset = 0; 
        
        // Allow counting to proceed for 100ns
        #100;
        
        // Apply reset in the middle of counting
        #10 reset = 1;
        #10 reset = 0; 
        
        
        #100;
        
        
        $finish;
    end

endmodule



// vvp counter_sim
// iverilog -o counter_sim IC7490.v IC7490TB.v
// vvp counter_sim
// gtkwave counter.vcd

Task 01/counter.vcd
$date
	Tue Oct 22 09:21:19 2024
$end
$version
	Icarus Verilog
$end
$timescale
	1s
$end
$scope module IC7490TB $end
$var wire 4 ! Q [3:0] $end
$var reg 1 " clk $end
$var reg 1 # reset $end
$scope module uut $end
$var wire 1 " clk $end
$var wire 1 # reset $end
$var reg 4 $ Q [3:0] $end
$upscope $end
$upscope $end
$enddefinitions $end
$comment Show the parameter values. $end
$dumpall
$end
#0
$dumpvars
b0 $
1#
0"
b0 !
$end
#5
1"
#10
0"
0#
#15
b1 !
b1 $
1"
#20
0"
#25
b10 !
b10 $
1"
#30
0"
#35
b11 !
b11 $
1"
#40
0"
#45
b100 !
b100 $
1"
#50
0"
#55
b101 !
b101 $
1"
#60
0"
#65
b110 !
b110 $
1"
#70
0"
#75
b111 !
b111 $
1"
#80
0"
#85
b1000 !
b1000 $
1"
#90
0"
#95
b1001 !
b1001 $
1"
#100
0"
#105
b0 !
b0 $
1"
#110
0"
#115
b1 !
b1 $
1"
#120
b0 !
b0 $
0"
1#
#125
1"
#130
0"
0#
#135
b1 !
b1 $
1"
#140
0"
#145
b10 !
b10 $
1"
#150
0"
#155
b11 !
b11 $
1"
#160
0"
#165
b100 !
b100 $
1"
#170
0"
#175
b101 !
b101 $
1"
#180
0"
#185
b110 !
b110 $
1"
#190
0"
#195
b111 !
b111 $
1"
#200
0"
#205
b1000 !
b1000 $
1"
#210
0"
#215
b1001 !
b1001 $
1"
#220
0"
#225
b0 !
b0 $
1"
